{"name":"Cpp","tagline":"","body":"# C++ gyakorlat 2015/16 1. félév\r\nELTE Informatikai Kar\r\n\r\n## Információk\r\n - Helyszín: Péntek 10:00-11:30 00-114 terem\r\n - Számonkérés\r\n    - 4 db pluszminusz\r\n    - a vizsga előtt egy elméleti beugró\r\n    - a vizsga egy C++ programozási feladat\r\n\r\n## A repository anyaga\r\n  - A példák letölthetőek a https://github.com/agobi/cpp oldalon\r\n  - `git clone https://github.com/agobi/cpp` paranccsal\r\n","google":"UA-67479606-1","note":"Don't delete this file! It's used internally to help with page regeneration."}